gboost_module/__init__.py
gboost_module/lgbmodule.py
gboost_module/xgbmodule.py
gboost_module/experimental/__init__.py
gboost_module/experimental/catmodule.py
gboost_module/models/__init__.py
gboost_module/models/forecasting.py
gboost_module/models/tests/__init__.py
gboost_module/models/tests/test_forecasting.py
gboost_module/tests/__init__.py
gboost_module/tests/test_lgbmodule.py
gboost_module/tests/test_readme_examples.py
gboost_module/tests/test_xgbmodule.py
gboost_module/tests/experimental/__init__.py
gboost_module/tests/experimental/test_catmodule.py
gboost_module-0.1.4.dist-info/LICENSE
gboost_module-0.1.4.dist-info/METADATA
gboost_module-0.1.4.dist-info/WHEEL
gboost_module-0.1.4.dist-info/top_level.txt
gboost_module-0.1.4.dist-info/RECORD
