Metadata-Version: 2.1
Name: gboost_module
Version: 0.1.4
Summary: Torch modules using popular boosting libraries
Home-page: https://github.com/mthorrell/gboost_module
Author: Michael Horrell
Author-email: mthorrell@github.com
License-File: LICENSE
Requires-Dist: numpy
Requires-Dist: torch
